transparentai/__init__.py
transparentai/datasets/ClassificationDataset.py
transparentai/datasets/__init__.py
transparentai/datasets/classification_dataset.py
transparentai/datasets/datasets.py
transparentai/datasets/datasets_plots.py
transparentai/datasets/protected_attribute.py
transparentai/datasets/structured_dataset.py
transparentai/datasets/data/adult.csv
transparentai/datasets/data/boston.csv
transparentai/datasets/data/housing.csv
transparentai/datasets/data/iris.csv
transparentai/datasets/variable/__init__.py
transparentai/datasets/variable/correlation.py
transparentai/datasets/variable/variable.py
transparentai/datasets/variable/variable_plots.py
transparentai/explainer/__init__.py
transparentai/explainer/explainer_plots.py
transparentai/explainer/model_explainer.py
transparentai/explore/__init__.py
transparentai/explore/explore.py
transparentai/fairness/__init__.py
transparentai/fairness/bias_metric.py
transparentai/fairness/dataset_bias_metric.py
transparentai/fairness/dataset_protected_attribute.py
transparentai/fairness/fairness.py
transparentai/fairness/fairness_plots.py
transparentai/fairness/metrics.py
transparentai/fairness/model_bias_metric.py
transparentai/fairness/model_protected_attribute.py
transparentai/fairness/protected_attribute.py
transparentai/models/__init__.py
transparentai/models/base_model.py
transparentai/models/classification_model.py
transparentai/models/models_plots.py
transparentai/models/regression_model.py
transparentai/models/classification/__init__.py
transparentai/models/classification/classification_plots.py
transparentai/models/classification/metrics.py
transparentai/models/evaluation/__init__.py
transparentai/models/evaluation/classification.py
transparentai/models/evaluation/evaluation.py
transparentai/models/evaluation/regression.py
transparentai/models/explainers/__init__.py
transparentai/models/explainers/explainer_plots.py
transparentai/models/explainers/model_explainer.py
transparentai/models/regression/__init__.py
transparentai-0.2.1.dist-info/LICENSE
transparentai-0.2.1.dist-info/METADATA
transparentai-0.2.1.dist-info/WHEEL
transparentai-0.2.1.dist-info/top_level.txt
transparentai-0.2.1.dist-info/RECORD
