Metadata-Version: 2.1
Name: transparentai
Version: 0.2.1
Summary: Python tool to create or inspect a transparent and ethical AI.
Home-page: https://github.com/Nathanlauga/transparentai
Author: Nathan LAUGA
Author-email: nathan.lauga@protonmail.com
License: MIT
Platform: UNKNOWN
Classifier: Topic :: Software Development :: Libraries :: Python Modules
Classifier: License :: OSI Approved :: MIT License
Classifier: Programming Language :: Python :: 3
Requires-Python: >=3.6
Requires-Dist: energyusage
Requires-Dist: ipywidgets
Requires-Dist: matplotlib
Requires-Dist: numpy
Requires-Dist: pandas
Requires-Dist: safety
Requires-Dist: scikit-learn
Requires-Dist: seaborn
Requires-Dist: shap
